{
  "version": "7",
  "dialect": "postgresql",
  "entries": [
    {
      "idx": 0,
      "version": "7",
      "when": 1773401232135,
      "tag": "0000_init",
      "breakpoints": true
    },
    {
      "idx": 1,
      "version": "7",
      "when": 1744444800000,
      "tag": "0001_add_payment_request_columns",
      "breakpoints": true
    },
    {
      "idx": 2,
      "version": "7",
      "when": 1747526400000,
      "tag": "0002_business_only_refactor",
      "breakpoints": true
    },
    {
      "idx": 3,
      "version": "7",
      "when": 1747612800000,
      "tag": "0003_device_sessions",
      "breakpoints": true
    },
    {
      "idx": 4,
      "version": "7",
      "when": 1747699200000,
      "tag": "0004_device_pairing_requests",
      "breakpoints": true
    },
    {
      "idx": 5,
      "version": "7",
      "when": 1748908800000,
      "tag": "0005_business_treasuries",
      "breakpoints": true
    },
    {
      "idx": 6,
      "version": "7",
      "when": 1748995200000,
      "tag": "0006_treasury_roles",
      "breakpoints": true
    }
  ]
}